EasyUI/README.md
EasyUI/__init__.py
EasyUI/designer.py
EasyUI/library.py
easyui_python-1.2.0.dist-info/METADATA
easyui_python-1.2.0.dist-info/WHEEL
easyui_python-1.2.0.dist-info/entry_points.txt
easyui_python-1.2.0.dist-info/top_level.txt
easyui_python-1.2.0.dist-info/RECORD
