Metadata-Version: 2.1
Name: easyui-python
Version: 1.2.0
Summary: Easy Python GUI Designers and Libraries
Home-page: https://github.com/sjn8623-collab/EasyUI
Author: kdh
Requires-Python: >=3.6
Requires-Dist: Pillow
Requires-Dist: tkinterdnd2
